fastgithub/__init__.py
fastgithub/_version.py
fastgithub/py.typed
fastgithub/types.py
fastgithub/endpoint/__init__.py
fastgithub/endpoint/helper.py
fastgithub/endpoint/webhook_router.py
fastgithub/helpers/__init__.py
fastgithub/helpers/github.py
fastgithub/recipes/__init__.py
fastgithub/recipes/_base.py
fastgithub/recipes/github/__init__.py
fastgithub/recipes/github/_config.py
fastgithub/recipes/github/autocreate_pr.py
fastgithub/recipes/github/labels_from_commits.py
fastgithub/webhook/__init__.py
fastgithub/webhook/handler.py
fastgithub/webhook/signature.py
fastgithub-0.0.6.dist-info/METADATA
fastgithub-0.0.6.dist-info/WHEEL
fastgithub-0.0.6.dist-info/licenses/LICENSE
fastgithub-0.0.6.dist-info/RECORD
