Metadata-Version: 2.4
Name: fastgithub
Version: 0.0.6
Summary: A Python library to supercharge your GitHub organization with bots and webhooks. 
Project-URL: Homepage, https://github.com/VDuchauffour/fastgithub
Project-URL: Documentation, https://github.com/VDuchauffour/fastgithub
Author-email: Vincent Duchauffour <vincent.duchauffour@proton.me>
License: MIT License
License-File: LICENSE
Keywords: automation,bot,ci,fastapi,github,web,webhook
Classifier: Environment :: Web Environment
Classifier: Framework :: FastAPI
Classifier: Intended Audience :: Developers
Classifier: License :: OSI Approved :: MIT License
Classifier: Operating System :: OS Independent
Classifier: Programming Language :: Python
Classifier: Programming Language :: Python :: 3.12
Classifier: Programming Language :: Python :: 3.13
Requires-Python: >=3.12
Requires-Dist: fastapi[standard]>=0.116.1
Requires-Dist: pydantic>=2.9.2
Requires-Dist: pygithub>=2.6.1
